{
  "title": "Track 7",
  "artist": "Unknown",
  "bpm": 92,
  "duration": 97.75,
  "notes": [
    {
      "time": 0.258,
      "lane": 2,
      "duration": 0.0
    },
    {
      "time": 0.583,
      "lane": 0,
      "duration": 0.2
    },
    {
      "time": 0.908,
      "lane": 2,
      "duration": 0.0
    },
    {
      "time": 1.071,
      "lane": 3,
      "duration": 0.2
    },
    {
      "time": 1.071,
      "lane": 2,
      "duration": 0.0
    },
    {
      "time": 1.233,
      "lane": 1,
      "duration": 0.0
    },
    {
      "time": 1.396,
      "lane": 0,
      "duration": 0.2
    },
    {
      "time": 1.721,
      "lane": 3,
      "duration": 0.2
    },
    {
      "time": 1.721,
      "lane": 2,
      "duration": 0.0
    },
    {
      "time": 2.046,
      "lane": 1,
      "duration": 0.0
    },
    {
      "time": 2.371,
      "lane": 3,
      "duration": 0.2
    },
    {
      "time": 2.696,
      "lane": 1,
      "duration": 0.0
    },
    {
      "time": 3.021,
      "lane": 3,
      "duration": 0.2
    },
    {
      "time": 3.021,
      "lane": 2,
      "duration": 0.0
    },
    {
      "time": 3.346,
      "lane": 0,
      "duration": 0.2
    },
    {
      "time": 3.346,
      "lane": 1,
      "duration": 0.0
    },
    {
      "time": 3.671,
      "lane": 2,
      "duration": 0.0
    },
    {
      "time": 3.834,
      "lane": 1,
      "duration": 0.0
    },
    {
      "time": 3.997,
      "lane": 0,
      "duration": 0.2
    },
    {
      "time": 4.322,
      "lane": 2,
      "duration": 0.0
    },
    {
      "time": 4.484,
      "lane": 0,
      "duration": 0.2
    },
    {
      "time": 4.484,
      "lane": 1,
      "duration": 0.0
    },
    {
      "time": 4.647,
      "lane": 1,
      "duration": 0.0
    },
    {
      "time": 4.809,
      "lane": 3,
      "duration": 0.2
    },
    {
      "time": 4.972,
      "lane": 2,
      "duration": 0.0
    },
    {
      "time": 5.134,
      "lane": 0,
      "duration": 0.2
    },
    {
      "time": 5.134,
      "lane": 1,
      "duration": 0.0
    },
    {
      "time": 5.459,
      "lane": 2,
      "duration": 0.0
    },
    {
      "time": 5.622,
      "lane": 3,
      "duration": 0.2
    },
    {
      "time": 5.622,
      "lane": 2,
      "duration": 0.0
    },
    {
      "time": 5.784,
      "lane": 0,
      "duration": 0.2
    },
    {
      "time": 6.11,
      "lane": 2,
      "duration": 0.0
    },
    {
      "time": 6.272,
      "lane": 2,
      "duration": 0.0
    },
    {
      "time": 6.435,
      "lane": 1,
      "duration": 0.0
    },
    {
      "time": 6.76,
      "lane": 3,
      "duration": 0.2
    },
    {
      "time": 6.76,
      "lane": 2,
      "duration": 0.0
    },
    {
      "time": 7.247,
      "lane": 1,
      "duration": 0.0
    },
    {
      "time": 7.41,
      "lane": 3,
      "duration": 0.2
    },
    {
      "time": 7.897,
      "lane": 0,
      "duration": 0.2
    },
    {
      "time": 7.897,
      "lane": 1,
      "duration": 0.0
    },
    {
      "time": 8.06,
      "lane": 2,
      "duration": 0.0
    },
    {
      "time": 8.223,
      "lane": 3,
      "duration": 0.2
    },
    {
      "time": 8.385,
      "lane": 1,
      "duration": 0.0
    },
    {
      "time": 8.548,
      "lane": 0,
      "duration": 0.2
    },
    {
      "time": 8.548,
      "lane": 1,
      "duration": 0.0
    },
    {
      "time": 8.873,
      "lane": 2,
      "duration": 0.0
    },
    {
      "time": 9.198,
      "lane": 0,
      "duration": 0.2
    },
    {
      "time": 9.36,
      "lane": 2,
      "duration": 0.0
    },
    {
      "time": 9.685,
      "lane": 0,
      "duration": 0.2
    },
    {
      "time": 9.685,
      "lane": 1,
      "duration": 0.0
    },
    {
      "time": 9.848,
      "lane": 1,
      "duration": 0.0
    },
    {
      "time": 10.336,
      "lane": 0,
      "duration": 0.2
    },
    {
      "time": 10.336,
      "lane": 1,
      "duration": 0.0
    },
    {
      "time": 10.661,
      "lane": 2,
      "duration": 0.0
    },
    {
      "time": 10.823,
      "lane": 3,
      "duration": 0.2
    },
    {
      "time": 10.823,
      "lane": 2,
      "duration": 0.0
    },
    {
      "time": 11.148,
      "lane": 1,
      "duration": 0.0
    },
    {
      "time": 11.311,
      "lane": 3,
      "duration": 0.2
    },
    {
      "time": 11.311,
      "lane": 2,
      "duration": 0.0
    },
    {
      "time": 11.473,
      "lane": 2,
      "duration": 0.0
    },
    {
      "time": 11.636,
      "lane": 0,
      "duration": 0.2
    },
    {
      "time": 11.798,
      "lane": 1,
      "duration": 0.0
    },
    {
      "time": 11.961,
      "lane": 3,
      "duration": 0.2
    },
    {
      "time": 11.961,
      "lane": 2,
      "duration": 0.0
    },
    {
      "time": 12.286,
      "lane": 1,
      "duration": 0.0
    },
    {
      "time": 12.611,
      "lane": 3,
      "duration": 0.2
    },
    {
      "time": 12.611,
      "lane": 2,
      "duration": 0.0
    },
    {
      "time": 12.774,
      "lane": 2,
      "duration": 0.0
    },
    {
      "time": 13.099,
      "lane": 1,
      "duration": 0.0
    },
    {
      "time": 13.749,
      "lane": 0,
      "duration": 0.2
    },
    {
      "time": 13.749,
      "lane": 1,
      "duration": 0.0
    },
    {
      "time": 14.074,
      "lane": 3,
      "duration": 0.2
    },
    {
      "time": 14.074,
      "lane": 2,
      "duration": 0.0
    },
    {
      "time": 14.399,
      "lane": 0,
      "duration": 0.2
    },
    {
      "time": 14.399,
      "lane": 1,
      "duration": 0.0
    },
    {
      "time": 14.562,
      "lane": 2,
      "duration": 0.0
    },
    {
      "time": 14.724,
      "lane": 3,
      "duration": 0.2
    },
    {
      "time": 15.049,
      "lane": 1,
      "duration": 0.0
    },
    {
      "time": 15.212,
      "lane": 3,
      "duration": 0.2
    },
    {
      "time": 15.374,
      "lane": 3,
      "duration": 0.2
    },
    {
      "time": 15.374,
      "lane": 2,
      "duration": 0.0
    },
    {
      "time": 15.699,
      "lane": 0,
      "duration": 0.2
    },
    {
      "time": 16.024,
      "lane": 3,
      "duration": 0.2
    },
    {
      "time": 16.35,
      "lane": 1,
      "duration": 0.0
    },
    {
      "time": 16.512,
      "lane": 3,
      "duration": 0.2
    },
    {
      "time": 16.512,
      "lane": 2,
      "duration": 0.0
    },
    {
      "time": 17.487,
      "lane": 0,
      "duration": 0.2
    },
    {
      "time": 17.487,
      "lane": 1,
      "duration": 0.0
    },
    {
      "time": 17.812,
      "lane": 3,
      "duration": 0.2
    },
    {
      "time": 18.137,
      "lane": 0,
      "duration": 0.2
    },
    {
      "time": 18.463,
      "lane": 3,
      "duration": 0.2
    },
    {
      "time": 18.788,
      "lane": 0,
      "duration": 0.2
    },
    {
      "time": 18.788,
      "lane": 1,
      "duration": 0.0
    },
    {
      "time": 19.113,
      "lane": 3,
      "duration": 0.2
    },
    {
      "time": 19.113,
      "lane": 2,
      "duration": 0.0
    },
    {
      "time": 19.438,
      "lane": 0,
      "duration": 0.2
    },
    {
      "time": 19.925,
      "lane": 3,
      "duration": 0.2
    },
    {
      "time": 19.925,
      "lane": 2,
      "duration": 0.0
    },
    {
      "time": 20.901,
      "lane": 0,
      "duration": 0.2
    },
    {
      "time": 20.901,
      "lane": 1,
      "duration": 0.0
    },
    {
      "time": 21.226,
      "lane": 3,
      "duration": 0.2
    },
    {
      "time": 21.226,
      "lane": 2,
      "duration": 0.0
    },
    {
      "time": 21.388,
      "lane": 1,
      "duration": 0.0
    },
    {
      "time": 21.551,
      "lane": 0,
      "duration": 0.2
    },
    {
      "time": 21.551,
      "lane": 1,
      "duration": 0.0
    },
    {
      "time": 21.876,
      "lane": 3,
      "duration": 0.2
    },
    {
      "time": 21.876,
      "lane": 2,
      "duration": 0.0
    },
    {
      "time": 22.201,
      "lane": 0,
      "duration": 0.2
    },
    {
      "time": 22.201,
      "lane": 1,
      "duration": 0.0
    },
    {
      "time": 22.526,
      "lane": 3,
      "duration": 0.2
    },
    {
      "time": 22.526,
      "lane": 2,
      "duration": 0.0
    },
    {
      "time": 22.851,
      "lane": 0,
      "duration": 0.2
    },
    {
      "time": 23.176,
      "lane": 2,
      "duration": 0.0
    },
    {
      "time": 23.339,
      "lane": 0,
      "duration": 0.2
    },
    {
      "time": 23.339,
      "lane": 1,
      "duration": 0.0
    },
    {
      "time": 23.501,
      "lane": 0,
      "duration": 0.2
    },
    {
      "time": 23.989,
      "lane": 0,
      "duration": 0.2
    },
    {
      "time": 24.314,
      "lane": 3,
      "duration": 0.2
    },
    {
      "time": 24.477,
      "lane": 2,
      "duration": 0.0
    },
    {
      "time": 24.639,
      "lane": 0,
      "duration": 0.2
    },
    {
      "time": 24.639,
      "lane": 1,
      "duration": 0.0
    },
    {
      "time": 24.802,
      "lane": 1,
      "duration": 0.0
    },
    {
      "time": 24.964,
      "lane": 3,
      "duration": 0.2
    },
    {
      "time": 25.289,
      "lane": 1,
      "duration": 0.0
    },
    {
      "time": 25.452,
      "lane": 0,
      "duration": 0.2
    },
    {
      "time": 25.452,
      "lane": 1,
      "duration": 0.0
    },
    {
      "time": 25.614,
      "lane": 3,
      "duration": 0.2
    },
    {
      "time": 25.614,
      "lane": 2,
      "duration": 0.0
    },
    {
      "time": 25.939,
      "lane": 1,
      "duration": 0.0
    },
    {
      "time": 26.102,
      "lane": 0,
      "duration": 0.2
    },
    {
      "time": 26.102,
      "lane": 1,
      "duration": 0.0
    },
    {
      "time": 26.264,
      "lane": 3,
      "duration": 0.2
    },
    {
      "time": 26.264,
      "lane": 2,
      "duration": 0.0
    },
    {
      "time": 26.752,
      "lane": 0,
      "duration": 0.2
    },
    {
      "time": 26.752,
      "lane": 1,
      "duration": 0.0
    },
    {
      "time": 27.24,
      "lane": 1,
      "duration": 0.0
    },
    {
      "time": 27.402,
      "lane": 0,
      "duration": 0.2
    },
    {
      "time": 27.727,
      "lane": 3,
      "duration": 0.2
    },
    {
      "time": 27.89,
      "lane": 0,
      "duration": 0.2
    },
    {
      "time": 28.052,
      "lane": 0,
      "duration": 0.2
    },
    {
      "time": 28.215,
      "lane": 2,
      "duration": 0.0
    },
    {
      "time": 28.54,
      "lane": 0,
      "duration": 0.2
    },
    {
      "time": 28.865,
      "lane": 3,
      "duration": 0.2
    },
    {
      "time": 29.028,
      "lane": 3,
      "duration": 0.2
    },
    {
      "time": 29.19,
      "lane": 0,
      "duration": 0.2
    },
    {
      "time": 29.19,
      "lane": 1,
      "duration": 0.0
    },
    {
      "time": 29.515,
      "lane": 3,
      "duration": 0.2
    },
    {
      "time": 29.515,
      "lane": 2,
      "duration": 0.0
    },
    {
      "time": 29.678,
      "lane": 3,
      "duration": 0.2
    },
    {
      "time": 30.816,
      "lane": 3,
      "duration": 0.2
    },
    {
      "time": 30.816,
      "lane": 2,
      "duration": 0.0
    },
    {
      "time": 31.141,
      "lane": 0,
      "duration": 0.2
    },
    {
      "time": 31.466,
      "lane": 3,
      "duration": 0.2
    },
    {
      "time": 31.953,
      "lane": 0,
      "duration": 0.2
    },
    {
      "time": 32.278,
      "lane": 2,
      "duration": 0.0
    },
    {
      "time": 32.604,
      "lane": 0,
      "duration": 0.2
    },
    {
      "time": 32.604,
      "lane": 1,
      "duration": 0.0
    },
    {
      "time": 32.929,
      "lane": 3,
      "duration": 0.2
    },
    {
      "time": 32.929,
      "lane": 2,
      "duration": 0.0
    },
    {
      "time": 33.254,
      "lane": 0,
      "duration": 0.2
    },
    {
      "time": 33.579,
      "lane": 3,
      "duration": 0.2
    },
    {
      "time": 33.579,
      "lane": 2,
      "duration": 0.0
    },
    {
      "time": 33.904,
      "lane": 1,
      "duration": 0.0
    },
    {
      "time": 34.229,
      "lane": 3,
      "duration": 0.2
    },
    {
      "time": 34.229,
      "lane": 2,
      "duration": 0.0
    },
    {
      "time": 34.554,
      "lane": 0,
      "duration": 0.2
    },
    {
      "time": 34.879,
      "lane": 3,
      "duration": 0.2
    },
    {
      "time": 34.879,
      "lane": 2,
      "duration": 0.0
    },
    {
      "time": 35.204,
      "lane": 1,
      "duration": 0.0
    },
    {
      "time": 35.367,
      "lane": 3,
      "duration": 0.2
    },
    {
      "time": 35.367,
      "lane": 2,
      "duration": 0.0
    },
    {
      "time": 35.692,
      "lane": 0,
      "duration": 0.2
    },
    {
      "time": 35.854,
      "lane": 0,
      "duration": 0.2
    },
    {
      "time": 36.017,
      "lane": 3,
      "duration": 0.2
    },
    {
      "time": 36.017,
      "lane": 2,
      "duration": 0.0
    },
    {
      "time": 36.342,
      "lane": 0,
      "duration": 0.2
    },
    {
      "time": 36.342,
      "lane": 1,
      "duration": 0.0
    },
    {
      "time": 36.667,
      "lane": 3,
      "duration": 0.2
    },
    {
      "time": 36.667,
      "lane": 2,
      "duration": 0.0
    },
    {
      "time": 36.83,
      "lane": 2,
      "duration": 0.0
    },
    {
      "time": 37.642,
      "lane": 0,
      "duration": 0.2
    },
    {
      "time": 37.642,
      "lane": 1,
      "duration": 0.0
    },
    {
      "time": 37.967,
      "lane": 3,
      "duration": 0.2
    },
    {
      "time": 37.967,
      "lane": 2,
      "duration": 0.0
    },
    {
      "time": 38.13,
      "lane": 2,
      "duration": 0.0
    },
    {
      "time": 38.292,
      "lane": 0,
      "duration": 0.2
    },
    {
      "time": 38.617,
      "lane": 2,
      "duration": 0.0
    },
    {
      "time": 38.78,
      "lane": 3,
      "duration": 0.2
    },
    {
      "time": 38.943,
      "lane": 1,
      "duration": 0.0
    },
    {
      "time": 39.105,
      "lane": 0,
      "duration": 0.2
    },
    {
      "time": 39.268,
      "lane": 2,
      "duration": 0.0
    },
    {
      "time": 39.43,
      "lane": 3,
      "duration": 0.2
    },
    {
      "time": 39.43,
      "lane": 2,
      "duration": 0.0
    },
    {
      "time": 39.593,
      "lane": 1,
      "duration": 0.0
    },
    {
      "time": 39.755,
      "lane": 0,
      "duration": 0.2
    },
    {
      "time": 39.918,
      "lane": 2,
      "duration": 0.0
    },
    {
      "time": 40.08,
      "lane": 3,
      "duration": 0.2
    },
    {
      "time": 40.243,
      "lane": 0,
      "duration": 0.2
    },
    {
      "time": 40.243,
      "lane": 1,
      "duration": 0.0
    },
    {
      "time": 40.405,
      "lane": 1,
      "duration": 0.0
    },
    {
      "time": 41.056,
      "lane": 0,
      "duration": 0.2
    },
    {
      "time": 41.056,
      "lane": 1,
      "duration": 0.0
    },
    {
      "time": 41.543,
      "lane": 0,
      "duration": 0.2
    },
    {
      "time": 41.543,
      "lane": 1,
      "duration": 0.0
    },
    {
      "time": 41.706,
      "lane": 0,
      "duration": 0.2
    },
    {
      "time": 42.031,
      "lane": 2,
      "duration": 0.0
    },
    {
      "time": 42.193,
      "lane": 0,
      "duration": 0.2
    },
    {
      "time": 42.356,
      "lane": 0,
      "duration": 0.2
    },
    {
      "time": 42.356,
      "lane": 1,
      "duration": 0.0
    },
    {
      "time": 42.681,
      "lane": 3,
      "duration": 0.2
    },
    {
      "time": 42.681,
      "lane": 2,
      "duration": 0.0
    },
    {
      "time": 43.169,
      "lane": 3,
      "duration": 0.2
    },
    {
      "time": 43.169,
      "lane": 2,
      "duration": 0.0
    },
    {
      "time": 43.331,
      "lane": 2,
      "duration": 0.0
    },
    {
      "time": 43.494,
      "lane": 0,
      "duration": 0.2
    },
    {
      "time": 43.819,
      "lane": 2,
      "duration": 0.0
    },
    {
      "time": 43.981,
      "lane": 3,
      "duration": 0.2
    },
    {
      "time": 43.981,
      "lane": 2,
      "duration": 0.0
    },
    {
      "time": 44.144,
      "lane": 1,
      "duration": 0.0
    },
    {
      "time": 44.306,
      "lane": 0,
      "duration": 0.2
    },
    {
      "time": 44.631,
      "lane": 2,
      "duration": 0.0
    },
    {
      "time": 44.957,
      "lane": 1,
      "duration": 0.0
    },
    {
      "time": 45.119,
      "lane": 3,
      "duration": 0.2
    },
    {
      "time": 45.444,
      "lane": 1,
      "duration": 0.0
    },
    {
      "time": 45.607,
      "lane": 0,
      "duration": 0.2
    },
    {
      "time": 45.769,
      "lane": 3,
      "duration": 0.2
    },
    {
      "time": 45.769,
      "lane": 2,
      "duration": 0.0
    },
    {
      "time": 46.094,
      "lane": 0,
      "duration": 0.2
    },
    {
      "time": 46.094,
      "lane": 1,
      "duration": 0.0
    },
    {
      "time": 46.257,
      "lane": 0,
      "duration": 0.2
    },
    {
      "time": 46.582,
      "lane": 3,
      "duration": 0.2
    },
    {
      "time": 46.582,
      "lane": 2,
      "duration": 0.0
    },
    {
      "time": 46.744,
      "lane": 1,
      "duration": 0.0
    },
    {
      "time": 46.907,
      "lane": 0,
      "duration": 0.2
    },
    {
      "time": 47.07,
      "lane": 2,
      "duration": 0.0
    },
    {
      "time": 47.232,
      "lane": 2,
      "duration": 0.0
    },
    {
      "time": 47.395,
      "lane": 0,
      "duration": 0.2
    },
    {
      "time": 47.395,
      "lane": 1,
      "duration": 0.0
    },
    {
      "time": 47.557,
      "lane": 1,
      "duration": 0.0
    },
    {
      "time": 47.72,
      "lane": 2,
      "duration": 0.0
    },
    {
      "time": 47.882,
      "lane": 2,
      "duration": 0.0
    },
    {
      "time": 48.045,
      "lane": 0,
      "duration": 0.2
    },
    {
      "time": 48.37,
      "lane": 3,
      "duration": 0.2
    },
    {
      "time": 48.37,
      "lane": 2,
      "duration": 0.0
    },
    {
      "time": 48.532,
      "lane": 3,
      "duration": 0.2
    },
    {
      "time": 48.532,
      "lane": 2,
      "duration": 0.0
    },
    {
      "time": 49.02,
      "lane": 3,
      "duration": 0.2
    },
    {
      "time": 49.508,
      "lane": 1,
      "duration": 0.0
    },
    {
      "time": 49.67,
      "lane": 3,
      "duration": 0.2
    },
    {
      "time": 49.67,
      "lane": 2,
      "duration": 0.0
    },
    {
      "time": 49.995,
      "lane": 0,
      "duration": 0.2
    },
    {
      "time": 49.995,
      "lane": 1,
      "duration": 0.0
    },
    {
      "time": 50.32,
      "lane": 3,
      "duration": 0.2
    },
    {
      "time": 50.32,
      "lane": 2,
      "duration": 0.0
    },
    {
      "time": 50.808,
      "lane": 0,
      "duration": 0.2
    },
    {
      "time": 50.808,
      "lane": 1,
      "duration": 0.0
    },
    {
      "time": 51.458,
      "lane": 1,
      "duration": 0.0
    },
    {
      "time": 51.783,
      "lane": 3,
      "duration": 0.2
    },
    {
      "time": 51.783,
      "lane": 2,
      "duration": 0.0
    },
    {
      "time": 52.108,
      "lane": 0,
      "duration": 0.2
    },
    {
      "time": 52.108,
      "lane": 1,
      "duration": 0.0
    },
    {
      "time": 52.271,
      "lane": 2,
      "duration": 0.0
    },
    {
      "time": 52.433,
      "lane": 3,
      "duration": 0.2
    },
    {
      "time": 52.758,
      "lane": 1,
      "duration": 0.0
    },
    {
      "time": 52.921,
      "lane": 3,
      "duration": 0.2
    },
    {
      "time": 52.921,
      "lane": 2,
      "duration": 0.0
    },
    {
      "time": 53.084,
      "lane": 3,
      "duration": 0.2
    },
    {
      "time": 53.084,
      "lane": 2,
      "duration": 0.0
    },
    {
      "time": 53.409,
      "lane": 0,
      "duration": 0.2
    },
    {
      "time": 53.409,
      "lane": 1,
      "duration": 0.0
    },
    {
      "time": 53.734,
      "lane": 3,
      "duration": 0.2
    },
    {
      "time": 53.734,
      "lane": 2,
      "duration": 0.0
    },
    {
      "time": 54.059,
      "lane": 1,
      "duration": 0.0
    },
    {
      "time": 54.221,
      "lane": 3,
      "duration": 0.2
    },
    {
      "time": 54.221,
      "lane": 2,
      "duration": 0.0
    },
    {
      "time": 54.871,
      "lane": 3,
      "duration": 0.2
    },
    {
      "time": 55.197,
      "lane": 0,
      "duration": 0.2
    },
    {
      "time": 55.197,
      "lane": 1,
      "duration": 0.0
    },
    {
      "time": 55.684,
      "lane": 3,
      "duration": 0.2
    },
    {
      "time": 55.684,
      "lane": 2,
      "duration": 0.0
    },
    {
      "time": 55.847,
      "lane": 0,
      "duration": 0.2
    },
    {
      "time": 56.009,
      "lane": 1,
      "duration": 0.0
    },
    {
      "time": 56.172,
      "lane": 2,
      "duration": 0.0
    },
    {
      "time": 56.334,
      "lane": 3,
      "duration": 0.2
    },
    {
      "time": 56.334,
      "lane": 2,
      "duration": 0.0
    },
    {
      "time": 56.497,
      "lane": 0,
      "duration": 0.2
    },
    {
      "time": 56.822,
      "lane": 3,
      "duration": 0.2
    },
    {
      "time": 57.147,
      "lane": 0,
      "duration": 0.2
    },
    {
      "time": 57.147,
      "lane": 1,
      "duration": 0.0
    },
    {
      "time": 57.635,
      "lane": 3,
      "duration": 0.2
    },
    {
      "time": 57.635,
      "lane": 2,
      "duration": 0.0
    },
    {
      "time": 57.797,
      "lane": 1,
      "duration": 0.0
    },
    {
      "time": 58.122,
      "lane": 2,
      "duration": 0.0
    },
    {
      "time": 58.285,
      "lane": 2,
      "duration": 0.0
    },
    {
      "time": 58.447,
      "lane": 1,
      "duration": 0.0
    },
    {
      "time": 58.61,
      "lane": 0,
      "duration": 0.2
    },
    {
      "time": 58.61,
      "lane": 1,
      "duration": 0.0
    },
    {
      "time": 58.772,
      "lane": 2,
      "duration": 0.0
    },
    {
      "time": 59.097,
      "lane": 1,
      "duration": 0.0
    },
    {
      "time": 59.26,
      "lane": 0,
      "duration": 0.2
    },
    {
      "time": 59.585,
      "lane": 3,
      "duration": 0.2
    },
    {
      "time": 59.585,
      "lane": 2,
      "duration": 0.0
    },
    {
      "time": 59.91,
      "lane": 0,
      "duration": 0.2
    },
    {
      "time": 59.91,
      "lane": 1,
      "duration": 0.0
    },
    {
      "time": 60.235,
      "lane": 3,
      "duration": 0.2
    },
    {
      "time": 60.235,
      "lane": 2,
      "duration": 0.0
    },
    {
      "time": 60.723,
      "lane": 3,
      "duration": 0.2
    },
    {
      "time": 60.885,
      "lane": 2,
      "duration": 0.0
    },
    {
      "time": 61.048,
      "lane": 0,
      "duration": 0.2
    },
    {
      "time": 61.048,
      "lane": 1,
      "duration": 0.0
    },
    {
      "time": 61.21,
      "lane": 0,
      "duration": 0.2
    },
    {
      "time": 61.698,
      "lane": 0,
      "duration": 0.2
    },
    {
      "time": 62.023,
      "lane": 3,
      "duration": 0.2
    },
    {
      "time": 62.348,
      "lane": 0,
      "duration": 0.2
    },
    {
      "time": 62.673,
      "lane": 2,
      "duration": 0.0
    },
    {
      "time": 62.836,
      "lane": 3,
      "duration": 0.2
    },
    {
      "time": 62.998,
      "lane": 1,
      "duration": 0.0
    },
    {
      "time": 63.161,
      "lane": 0,
      "duration": 0.2
    },
    {
      "time": 63.161,
      "lane": 1,
      "duration": 0.0
    },
    {
      "time": 63.324,
      "lane": 3,
      "duration": 0.2
    },
    {
      "time": 63.324,
      "lane": 2,
      "duration": 0.0
    },
    {
      "time": 63.486,
      "lane": 3,
      "duration": 0.2
    },
    {
      "time": 63.811,
      "lane": 0,
      "duration": 0.2
    },
    {
      "time": 63.811,
      "lane": 1,
      "duration": 0.0
    },
    {
      "time": 63.974,
      "lane": 3,
      "duration": 0.2
    },
    {
      "time": 64.299,
      "lane": 1,
      "duration": 0.0
    },
    {
      "time": 64.461,
      "lane": 0,
      "duration": 0.2
    },
    {
      "time": 64.949,
      "lane": 1,
      "duration": 0.0
    },
    {
      "time": 65.111,
      "lane": 0,
      "duration": 0.2
    },
    {
      "time": 65.111,
      "lane": 1,
      "duration": 0.0
    },
    {
      "time": 65.437,
      "lane": 3,
      "duration": 0.2
    },
    {
      "time": 65.762,
      "lane": 0,
      "duration": 0.2
    },
    {
      "time": 65.924,
      "lane": 2,
      "duration": 0.0
    },
    {
      "time": 66.249,
      "lane": 0,
      "duration": 0.2
    },
    {
      "time": 66.249,
      "lane": 1,
      "duration": 0.0
    },
    {
      "time": 66.574,
      "lane": 2,
      "duration": 0.0
    },
    {
      "time": 66.899,
      "lane": 0,
      "duration": 0.2
    },
    {
      "time": 66.899,
      "lane": 1,
      "duration": 0.0
    },
    {
      "time": 67.224,
      "lane": 3,
      "duration": 0.2
    },
    {
      "time": 67.224,
      "lane": 2,
      "duration": 0.0
    },
    {
      "time": 67.55,
      "lane": 0,
      "duration": 0.2
    },
    {
      "time": 67.55,
      "lane": 1,
      "duration": 0.0
    },
    {
      "time": 67.875,
      "lane": 3,
      "duration": 0.2
    },
    {
      "time": 68.362,
      "lane": 0,
      "duration": 0.2
    },
    {
      "time": 68.362,
      "lane": 1,
      "duration": 0.0
    },
    {
      "time": 68.525,
      "lane": 3,
      "duration": 0.2
    },
    {
      "time": 68.85,
      "lane": 0,
      "duration": 0.2
    },
    {
      "time": 69.175,
      "lane": 3,
      "duration": 0.2
    },
    {
      "time": 69.663,
      "lane": 1,
      "duration": 0.0
    },
    {
      "time": 69.825,
      "lane": 3,
      "duration": 0.2
    },
    {
      "time": 69.825,
      "lane": 2,
      "duration": 0.0
    },
    {
      "time": 69.988,
      "lane": 3,
      "duration": 0.2
    },
    {
      "time": 70.15,
      "lane": 0,
      "duration": 0.2
    },
    {
      "time": 70.15,
      "lane": 1,
      "duration": 0.0
    },
    {
      "time": 70.313,
      "lane": 0,
      "duration": 0.2
    },
    {
      "time": 70.313,
      "lane": 1,
      "duration": 0.0
    },
    {
      "time": 70.638,
      "lane": 2,
      "duration": 0.0
    },
    {
      "time": 70.963,
      "lane": 0,
      "duration": 0.2
    },
    {
      "time": 71.45,
      "lane": 0,
      "duration": 0.2
    },
    {
      "time": 71.45,
      "lane": 1,
      "duration": 0.0
    },
    {
      "time": 71.613,
      "lane": 1,
      "duration": 0.0
    },
    {
      "time": 71.938,
      "lane": 3,
      "duration": 0.2
    },
    {
      "time": 71.938,
      "lane": 2,
      "duration": 0.0
    },
    {
      "time": 72.101,
      "lane": 0,
      "duration": 0.2
    },
    {
      "time": 72.263,
      "lane": 0,
      "duration": 0.2
    },
    {
      "time": 72.263,
      "lane": 1,
      "duration": 0.0
    },
    {
      "time": 72.426,
      "lane": 2,
      "duration": 0.0
    },
    {
      "time": 72.588,
      "lane": 3,
      "duration": 0.2
    },
    {
      "time": 72.913,
      "lane": 1,
      "duration": 0.0
    },
    {
      "time": 73.238,
      "lane": 3,
      "duration": 0.2
    },
    {
      "time": 73.238,
      "lane": 2,
      "duration": 0.0
    },
    {
      "time": 73.564,
      "lane": 1,
      "duration": 0.0
    },
    {
      "time": 73.726,
      "lane": 3,
      "duration": 0.2
    },
    {
      "time": 73.726,
      "lane": 2,
      "duration": 0.0
    },
    {
      "time": 73.889,
      "lane": 2,
      "duration": 0.0
    },
    {
      "time": 74.051,
      "lane": 0,
      "duration": 0.2
    },
    {
      "time": 74.051,
      "lane": 1,
      "duration": 0.0
    },
    {
      "time": 74.376,
      "lane": 3,
      "duration": 0.2
    },
    {
      "time": 74.701,
      "lane": 0,
      "duration": 0.2
    },
    {
      "time": 74.701,
      "lane": 1,
      "duration": 0.0
    },
    {
      "time": 75.026,
      "lane": 3,
      "duration": 0.2
    },
    {
      "time": 75.026,
      "lane": 2,
      "duration": 0.0
    },
    {
      "time": 75.189,
      "lane": 3,
      "duration": 0.2
    },
    {
      "time": 75.189,
      "lane": 2,
      "duration": 0.0
    },
    {
      "time": 75.351,
      "lane": 0,
      "duration": 0.2
    },
    {
      "time": 75.351,
      "lane": 1,
      "duration": 0.0
    },
    {
      "time": 75.677,
      "lane": 3,
      "duration": 0.2
    },
    {
      "time": 75.839,
      "lane": 2,
      "duration": 0.0
    },
    {
      "time": 76.002,
      "lane": 0,
      "duration": 0.2
    },
    {
      "time": 76.327,
      "lane": 2,
      "duration": 0.0
    },
    {
      "time": 76.489,
      "lane": 3,
      "duration": 0.2
    },
    {
      "time": 76.489,
      "lane": 2,
      "duration": 0.0
    },
    {
      "time": 76.652,
      "lane": 1,
      "duration": 0.0
    },
    {
      "time": 76.814,
      "lane": 0,
      "duration": 0.2
    },
    {
      "time": 76.977,
      "lane": 3,
      "duration": 0.2
    },
    {
      "time": 76.977,
      "lane": 2,
      "duration": 0.0
    },
    {
      "time": 77.464,
      "lane": 0,
      "duration": 0.2
    },
    {
      "time": 77.464,
      "lane": 1,
      "duration": 0.0
    },
    {
      "time": 77.79,
      "lane": 3,
      "duration": 0.2
    },
    {
      "time": 78.277,
      "lane": 2,
      "duration": 0.0
    },
    {
      "time": 78.44,
      "lane": 3,
      "duration": 0.2
    },
    {
      "time": 78.44,
      "lane": 2,
      "duration": 0.0
    },
    {
      "time": 78.602,
      "lane": 0,
      "duration": 0.2
    },
    {
      "time": 78.602,
      "lane": 1,
      "duration": 0.0
    },
    {
      "time": 78.765,
      "lane": 0,
      "duration": 0.2
    },
    {
      "time": 79.09,
      "lane": 3,
      "duration": 0.2
    },
    {
      "time": 79.252,
      "lane": 1,
      "duration": 0.0
    },
    {
      "time": 79.415,
      "lane": 0,
      "duration": 0.2
    },
    {
      "time": 79.415,
      "lane": 1,
      "duration": 0.0
    },
    {
      "time": 79.903,
      "lane": 0,
      "duration": 0.2
    },
    {
      "time": 79.903,
      "lane": 1,
      "duration": 0.0
    },
    {
      "time": 80.228,
      "lane": 3,
      "duration": 0.2
    },
    {
      "time": 80.553,
      "lane": 0,
      "duration": 0.2
    },
    {
      "time": 80.553,
      "lane": 1,
      "duration": 0.0
    },
    {
      "time": 80.715,
      "lane": 1,
      "duration": 0.0
    },
    {
      "time": 80.878,
      "lane": 3,
      "duration": 0.2
    },
    {
      "time": 80.878,
      "lane": 2,
      "duration": 0.0
    },
    {
      "time": 81.04,
      "lane": 2,
      "duration": 0.0
    },
    {
      "time": 81.69,
      "lane": 2,
      "duration": 0.0
    },
    {
      "time": 82.016,
      "lane": 0,
      "duration": 0.2
    },
    {
      "time": 82.016,
      "lane": 1,
      "duration": 0.0
    },
    {
      "time": 82.178,
      "lane": 3,
      "duration": 0.2
    },
    {
      "time": 82.178,
      "lane": 2,
      "duration": 0.0
    },
    {
      "time": 82.666,
      "lane": 0,
      "duration": 0.2
    },
    {
      "time": 82.666,
      "lane": 1,
      "duration": 0.0
    },
    {
      "time": 82.828,
      "lane": 3,
      "duration": 0.2
    },
    {
      "time": 82.991,
      "lane": 2,
      "duration": 0.0
    },
    {
      "time": 83.316,
      "lane": 0,
      "duration": 0.2
    },
    {
      "time": 83.316,
      "lane": 1,
      "duration": 0.0
    },
    {
      "time": 83.478,
      "lane": 2,
      "duration": 0.0
    },
    {
      "time": 83.641,
      "lane": 3,
      "duration": 0.2
    },
    {
      "time": 83.804,
      "lane": 0,
      "duration": 0.2
    },
    {
      "time": 83.966,
      "lane": 0,
      "duration": 0.2
    },
    {
      "time": 83.966,
      "lane": 1,
      "duration": 0.0
    },
    {
      "time": 84.291,
      "lane": 3,
      "duration": 0.2
    },
    {
      "time": 84.291,
      "lane": 2,
      "duration": 0.0
    },
    {
      "time": 84.454,
      "lane": 1,
      "duration": 0.0
    },
    {
      "time": 84.616,
      "lane": 0,
      "duration": 0.2
    },
    {
      "time": 84.779,
      "lane": 2,
      "duration": 0.0
    },
    {
      "time": 85.266,
      "lane": 1,
      "duration": 0.0
    },
    {
      "time": 85.591,
      "lane": 3,
      "duration": 0.2
    },
    {
      "time": 85.591,
      "lane": 2,
      "duration": 0.0
    },
    {
      "time": 85.754,
      "lane": 0,
      "duration": 0.2
    },
    {
      "time": 85.754,
      "lane": 1,
      "duration": 0.0
    },
    {
      "time": 86.079,
      "lane": 3,
      "duration": 0.2
    },
    {
      "time": 86.079,
      "lane": 2,
      "duration": 0.0
    },
    {
      "time": 86.404,
      "lane": 0,
      "duration": 0.2
    },
    {
      "time": 86.729,
      "lane": 3,
      "duration": 0.2
    },
    {
      "time": 86.729,
      "lane": 2,
      "duration": 0.0
    },
    {
      "time": 87.379,
      "lane": 3,
      "duration": 0.2
    },
    {
      "time": 87.379,
      "lane": 2,
      "duration": 0.0
    },
    {
      "time": 87.704,
      "lane": 0,
      "duration": 0.2
    },
    {
      "time": 87.704,
      "lane": 1,
      "duration": 0.0
    },
    {
      "time": 88.03,
      "lane": 3,
      "duration": 0.2
    },
    {
      "time": 88.517,
      "lane": 0,
      "duration": 0.2
    },
    {
      "time": 88.517,
      "lane": 1,
      "duration": 0.0
    },
    {
      "time": 88.842,
      "lane": 2,
      "duration": 0.0
    },
    {
      "time": 90.143,
      "lane": 3,
      "duration": 0.2
    },
    {
      "time": 90.143,
      "lane": 2,
      "duration": 0.0
    },
    {
      "time": 90.305,
      "lane": 0,
      "duration": 0.2
    },
    {
      "time": 90.305,
      "lane": 1,
      "duration": 0.0
    },
    {
      "time": 90.468,
      "lane": 1,
      "duration": 0.0
    },
    {
      "time": 90.793,
      "lane": 3,
      "duration": 0.2
    },
    {
      "time": 90.793,
      "lane": 2,
      "duration": 0.0
    },
    {
      "time": 91.28,
      "lane": 2,
      "duration": 0.0
    },
    {
      "time": 91.93,
      "lane": 3,
      "duration": 0.2
    },
    {
      "time": 92.093,
      "lane": 3,
      "duration": 0.2
    },
    {
      "time": 92.093,
      "lane": 2,
      "duration": 0.0
    },
    {
      "time": 92.581,
      "lane": 3,
      "duration": 0.2
    },
    {
      "time": 92.581,
      "lane": 2,
      "duration": 0.0
    },
    {
      "time": 92.906,
      "lane": 1,
      "duration": 0.0
    },
    {
      "time": 93.556,
      "lane": 0,
      "duration": 0.2
    },
    {
      "time": 93.718,
      "lane": 0,
      "duration": 0.2
    },
    {
      "time": 93.881,
      "lane": 2,
      "duration": 0.0
    },
    {
      "time": 94.206,
      "lane": 0,
      "duration": 0.2
    },
    {
      "time": 94.694,
      "lane": 2,
      "duration": 0.0
    },
    {
      "time": 95.344,
      "lane": 3,
      "duration": 0.2
    },
    {
      "time": 95.506,
      "lane": 0,
      "duration": 0.2
    },
    {
      "time": 95.506,
      "lane": 1,
      "duration": 0.0
    }
  ]
}
